LICENSE
README.md
setup.py
MRTHOIN_8.egg-info/PKG-INFO
MRTHOIN_8.egg-info/SOURCES.txt
MRTHOIN_8.egg-info/dependency_links.txt
MRTHOIN_8.egg-info/not-zip-safe
MRTHOIN_8.egg-info/requires.txt
MRTHOIN_8.egg-info/top_level.txt
libpythonpro/__init__.py
libpythonpro/github_api.py