Metadata-Version: 2.1
Name: MRTHOIN-8
Version: 0.1
Summary: Módulo para exemplificar construção de projetos Python no curso PyTools
Home-page: https://github.com/anthonysilvaa/libpythonpro
Author: Anthony Silva
Author-email: hedreson@icloud.com
License:                     GNU AFFERO GENERAL PUBLIC LICENSE
Platform: UNKNOWN
Classifier: Development Status :: 2 - Pre-Alpha
Classifier: Environment :: Console
Classifier: Intended Audience :: Developers
Classifier: License :: OSI Approved :: GNU Affero General Public License v3 or later (AGPLv3+)
Classifier: Operating System :: OS Independent
Classifier: Programming Language :: Python
Classifier: Programming Language :: Python :: 3.6
Classifier: Framework :: Pytest
License-File: LICENSE
